MANIFEST.in
README.md
pyproject.toml
setup.py
src/cynamedtuple/__init__.py
src/cynamedtuple/cynamedtuple.py
src/cynamedtuple.egg-info/PKG-INFO
src/cynamedtuple.egg-info/SOURCES.txt
src/cynamedtuple.egg-info/dependency_links.txt
src/cynamedtuple.egg-info/requires.txt
src/cynamedtuple.egg-info/top_level.txt