Metadata-Version: 2.1
Name: cynamedtuple
Version: 0.1.0
Summary: Memory efficient and fast namedtuple implementation using Cython
Home-page: https://github.com/realead/cynamedtuple
Author: Egor Dranischnikow
License: MIT
Platform: UNKNOWN
Classifier: Programming Language :: Python :: 3
